Pbls/__init__.py
Pbls/data/__init__.py
Pbls/data/data_loader.py
Pbls-0.0.1.dist-info/LICENSE
Pbls-0.0.1.dist-info/METADATA
Pbls-0.0.1.dist-info/WHEEL
Pbls-0.0.1.dist-info/top_level.txt
Pbls-0.0.1.dist-info/RECORD
