Metadata-Version: 2.1
Name: Pbls
Version: 0.0.1
Summary: DataClinic API packages
Author-email: Heeseok <heeseok.heo@pebblous.ai>
License: MIT License
Project-URL: Homepage, https://github.com/heeseok-pebblous/Pbls.git
Classifier: License :: OSI Approved :: MIT License
Classifier: Programming Language :: Python :: 3
Classifier: Operating System :: OS Independent
Requires-Python: >=3.7
License-File: LICENSE
Requires-Dist: requests >2.26.0
Requires-Dist: tqdm
Requires-Dist: paramiko
